{
  "experiment111": {
      "task": "virtual_floating_platform/MFP2D_Virtual_GoToXY",
      "train": "MFP2D_PPOmulti_dict_MLP",
      "experiment": "MLP_GTXY_UF_0.25_ST_PE_0.01_PAV_0.5_PLV_0.01",
      "headless": "True",
      "num_envs": "4096",
      "seed": 42,
      "max_iterations": "2000", 
      "task.env.split_thrust": "True",
      "task.env.use_uneven_floor": "True",
      "task.env.max_floor_force": 0.25,
      "task.env.penalties_parameters.penalize_energy": "True",
      "task.env.penalties_parameters.penalize_linear_velocity": "True",
      "task.env.penalties_parameters.penalize_angular_velocity": "True",
      "penalize_energy_fn": "lambda x: -torch.abs(x)*0.01",
      "penalize_linear_velocities_fn": "lambda x: -torch.norm(x, dim=-1)*0.01",
      "task.env.penalties_parameters.penalize_angular_velocities_fn": "1 + torch.tanh((12*x/2000 - 6)*0.5))/2",
      "wandb_activate": "True",
      "wandb_entity": "matteohariry",
      "wandb_project": "corl-2d-floating"
  },
  "experiment112": {
      "task": "virtual_floating_platform/MFP2D_Virtual_GoToXY",
      "train": "MFP2D_PPOmulti_dict_MLP",
      "experiment": "MLP_GTXY_UF_0.5_ST_PE_0.01_PAV_0.5_PLV_0.01",
      "headless": "True",
      "num_envs": "4096",
      "seed": 42,
      "max_iterations": "2000", 
      "task.env.split_thrust": "True",
      "task.env.use_uneven_floor": "True",
      "task.env.max_floor_force": 0.5,
      "task.env.penalties_parameters.penalize_energy": "True",
      "task.env.penalties_parameters.penalize_linear_velocity": "True",
      "task.env.penalties_parameters.penalize_angular_velocity": "True",
      "penalize_energy_fn": "lambda x: -torch.abs(x)*0.01",
      "penalize_linear_velocities_fn": "lambda x: -torch.norm(x, dim=-1)*0.01",
      "task.env.penalties_parameters.penalize_angular_velocities_fn": "1 + torch.tanh((12*x/2000 - 6)*0.5))/2",
      "wandb_activate": "True",
      "wandb_entity": "matteohariry",
      "wandb_project": "corl-2d-floating"
  },
  "experiment113": {
      "task": "virtual_floating_platform/MFP2D_Virtual_GoToXY",
      "train": "MFP2D_PPOmulti_dict_MLP",
      "experiment": "MLP_GTXY_UF_0.25_ST_PE_0.05_PAV_0.5_PLV_0.01",
      "headless": "True",
      "num_envs": "4096",
      "seed": 42,
      "max_iterations": "2000", 
      "task.env.split_thrust": "True",
      "task.env.use_uneven_floor": "True",
      "task.env.max_floor_force": 0.25,
      "task.env.penalties_parameters.penalize_energy": "True",
      "task.env.penalties_parameters.penalize_linear_velocity": "True",
      "task.env.penalties_parameters.penalize_angular_velocity": "True",
      "penalize_energy_fn": "lambda x: -torch.abs(x)*0.05",
      "penalize_linear_velocities_fn": "lambda x: -torch.norm(x, dim=-1)*0.01",
      "task.env.penalties_parameters.penalize_angular_velocities_fn": "1 + torch.tanh((12*x/2000 - 6)*0.5))/2",
      "wandb_activate": "True",
      "wandb_entity": "matteohariry",
      "wandb_project": "corl-2d-floating"
  },
  "experiment114": {
      "task": "virtual_floating_platform/MFP2D_Virtual_GoToXY",
      "train": "MFP2D_PPOmulti_dict_MLP",
      "experiment": "MLP_GTXY_UF_0.5_ST_PE_0.05_PAV_0.5_PLV_0.01",
      "headless": "True",
      "num_envs": "4096",
      "seed": 42,
      "max_iterations": "2000", 
      "task.env.split_thrust": "True",
      "task.env.use_uneven_floor": "True",
      "task.env.max_floor_force": 0.5,
      "task.env.penalties_parameters.penalize_energy": "True",
      "task.env.penalties_parameters.penalize_linear_velocity": "True",
      "task.env.penalties_parameters.penalize_angular_velocity": "True",
      "penalize_energy_fn": "lambda x: -torch.abs(x)*0.05",
      "penalize_linear_velocities_fn": "lambda x: -torch.norm(x, dim=-1)*0.01",
      "task.env.penalties_parameters.penalize_angular_velocities_fn": "1 + torch.tanh((12*x/2000 - 6)*0.5))/2",
      "wandb_activate": "True",
      "wandb_entity": "matteohariry",
      "wandb_project": "corl-2d-floating"
  },
  "experiment115": {
      "task": "virtual_floating_platform/MFP2D_Virtual_GoToXY",
      "train": "MFP2D_PPOmulti_dict_MLP",
      "experiment": "MLP_GTXY_UF_0.25_ST_PE_0.03_PAV_0.5_PLV_0.01",
      "headless": "True",
      "num_envs": "4096",
      "seed": 42,
      "max_iterations": "2000", 
      "task.env.split_thrust": "True",
      "task.env.use_uneven_floor": "True",
      "task.env.max_floor_force": 0.25,
      "task.env.penalties_parameters.penalize_energy": "True",
      "task.env.penalties_parameters.penalize_linear_velocity": "True",
      "task.env.penalties_parameters.penalize_angular_velocity": "True",
      "penalize_energy_fn": "lambda x: -torch.abs(x)*0.03",
      "penalize_linear_velocities_fn": "lambda x: -torch.norm(x, dim=-1)*0.01",
      "task.env.penalties_parameters.penalize_angular_velocities_fn": "1 + torch.tanh((12*x/2000 - 6)*0.5))/2",
      "wandb_activate": "True",
      "wandb_entity": "matteohariry",
      "wandb_project": "corl-2d-floating"
  },
  "experiment131": {
      "task": "virtual_floating_platform/MFP2D_Virtual_GoToXY",
      "train": "MFP2D_PPOmulti_dict_MLP",
      "experiment": "MLP_GTXY_UF_0.25_ST_PE_0.01_PAV_0.5_PLV_0.05",
      "headless": "True",
      "num_envs": "4096",
      "seed": 42,
      "max_iterations": "2000", 
      "task.env.split_thrust": "True",
      "task.env.use_uneven_floor": "True",
      "task.env.max_floor_force": 0.25,
      "task.env.penalties_parameters.penalize_energy": "True",
      "task.env.penalties_parameters.penalize_linear_velocity": "True",
      "task.env.penalties_parameters.penalize_angular_velocity": "True",
      "penalize_energy_fn": "lambda x: -torch.abs(x)*0.01",
      "penalize_linear_velocities_fn": "lambda x: -torch.norm(x, dim=-1)*0.05",
      "task.env.penalties_parameters.penalize_angular_velocities_fn": "1 + torch.tanh((12*x/2000 - 6)*0.5))/2",
      "wandb_activate": "True",
      "wandb_entity": "matteohariry",
      "wandb_project": "corl-2d-floating"
  },
  "experiment132": {
      "task": "virtual_floating_platform/MFP2D_Virtual_GoToXY",
      "train": "MFP2D_PPOmulti_dict_MLP",
      "experiment": "MLP_GTXY_UF_0.25_ST_PE_0.025_PAV_0.5_PLV_0.025",
      "headless": "True",
      "num_envs": "4096",
      "seed": 42,
      "max_iterations": "2000", 
      "task.env.split_thrust": "True",
      "task.env.use_uneven_floor": "True",
      "task.env.max_floor_force": 0.25,
      "task.env.penalties_parameters.penalize_energy": "True",
      "task.env.penalties_parameters.penalize_linear_velocity": "True",
      "task.env.penalties_parameters.penalize_angular_velocity": "True",
      "penalize_energy_fn": "lambda x: -torch.abs(x)*0.025",
      "penalize_linear_velocities_fn": "lambda x: -torch.norm(x, dim=-1)*0.025",
      "task.env.penalties_parameters.penalize_angular_velocities_fn": "1 + torch.tanh((12*x/2000 - 6)*0.5))/2",
      "wandb_activate": "True",
      "wandb_entity": "matteohariry",
      "wandb_project": "corl-2d-floating"
  }
}